gtdblib/__init__.py
gtdblib/__main__.py
gtdblib/cli/__init__.py
gtdblib/cli/tree.py
gtdblib/config.py
gtdblib/db/__init__.py
gtdblib/db/common.py
gtdblib/exception/__init__.py
gtdblib/file/__init__.py
gtdblib/file/itol/__init__.py
gtdblib/file/itol/collapse.py
gtdblib/file/itol/dataset_color_strip.py
gtdblib/file/itol/dataset_text.py
gtdblib/file/itol/label.py
gtdblib/file/itol/popup.py
gtdblib/file/itol/tree_colors.py
gtdblib/taxon/__init__.py
gtdblib/taxon/rank.py
gtdblib/taxon/taxon.py
gtdblib/taxonomy/__init__.py
gtdblib/taxonomy/taxonomy.py
gtdblib/taxonomy/validation.py
gtdblib/tree/__init__.py
gtdblib/tree/bootstrap_merge.py
gtdblib/tree/convert_accession.py
gtdblib/tree/get_node_depth.py
gtdblib/tree/get_node_to_desc_taxa.py
gtdblib/tree/get_unique_mrca_for_internal_nodes.py
gtdblib/tree/polytomy.py
gtdblib/util/__init__.py
gtdblib/util/bio/__init__.py
gtdblib/util/bio/accession.py
gtdblib/util/bio/exceptions.py
gtdblib/util/bio/newick.py
gtdblib/util/bio/seq_io.py
gtdblib/util/color.py
gtdblib/util/shell/__init__.py
gtdblib/util/shell/color.py
gtdblib/util/shell/execute.py
gtdblib/util/shell/filemgmt.py
gtdblib/util/shell/gtdbshutil.py
gtdblib/util/types.py
gtdblib-1.10.1.dist-info/LICENSE
gtdblib-1.10.1.dist-info/METADATA
gtdblib-1.10.1.dist-info/WHEEL
gtdblib-1.10.1.dist-info/entry_points.txt
gtdblib-1.10.1.dist-info/RECORD
